4-Bit counter/counter.v
module counter_4bit (
    input clk,
    input reset,
    output reg [3:0] count
);

always @(posedge clk or posedge reset) begin
    if (reset)
        count <= 4'b0000;
    else
        count <= count + 1;   // Increment counter
end

endmodule

4-Bit counter/counter4_tb.v
`timescale 1ns / 1ps

module tb_counter_4bit;

    reg clk;
    reg reset;
    wire [3:0] count;

    counter_4bit uut (
        .clk(clk),
        .reset(reset),
        .count(count)
    );

    initial begin
        clk = 0;
        forever #5 clk = ~clk; 
    end

    initial begin
        $dumpfile("dump.vcd");
        $dumpvars(0, tb_counter_4bit);
    end

    initial begin
        reset = 1;

        $display("Time(ns) | Reset | Count");
        $display("-------------------------");
        $monitor("%8t |   %b   | %4b (%0d)", $time, reset, count, count);

        #15; 
        reset = 0;

        #200;

        reset = 1;
        #12;
        reset = 0;
        
        #50;

        $display("--> Simulation complete.");
        $finish;
    end

endmodule

4-Bit counter/Obj_dir/dump.vcd
$version Generated by VerilatedVcd $end
$timescale 1ps $end

 $scope module TOP $end
  $scope module tb_counter_4bit $end
   $var wire  1 # clk $end
   $var wire  4 % count [3:0] $end
   $var wire  1 $ reset $end
   $scope module uut $end
    $var wire  1 # clk $end
    $var wire  4 % count [3:0] $end
    $var wire  1 $ reset $end
   $upscope $end
  $upscope $end
 $upscope $end
$enddefinitions $end


#0
0#
1$
b0000 %
#5000
1#
#10000
0#
#15000
1#
0$
b0001 %
#20000
0#
#25000
1#
b0010 %
#30000
0#
#35000
1#
b0011 %
#40000
0#
#45000
1#
b0100 %
#50000
0#
#55000
1#
b0101 %
#60000
0#
#65000
1#
b0110 %
#70000
0#
#75000
1#
b0111 %
#80000
0#
#85000
1#
b1000 %
#90000
0#
#95000
1#
b1001 %
#100000
0#
#105000
1#
b1010 %
#110000
0#
#115000
1#
b1011 %
#120000
0#
#125000
1#
b1100 %
#130000
0#
#135000
1#
b1101 %
#140000
0#
#145000
1#
b1110 %
#150000
0#
#155000
1#
b1111 %
#160000
0#
#165000
1#
b0000 %
#170000
0#
#175000
1#
b0001 %
#180000
0#
#185000
1#
b0010 %
#190000
0#
#195000
1#
b0011 %
#200000
0#
#205000
1#
b0100 %
#210000
0#
#215000
1#
1$
b0000 %
#220000
0#
#225000
1#
#227000
0$
#230000
0#
#235000
1#
b0001 %
#240000
0#
#245000
1#
b0010 %
#250000
0#
#255000
1#
b0011 %
#260000
0#
#265000
1#
b0100 %
#270000
0#
#275000
1#
b0101 %
